main.py
fsbridge-0.1.0.dist-info/licenses/LICENSE
fsbridge-0.1.0.dist-info/METADATA
fsbridge-0.1.0.dist-info/WHEEL
fsbridge-0.1.0.dist-info/top_level.txt
fsbridge-0.1.0.dist-info/RECORD
