Metadata-Version: 2.4
Name: fsbridge
Version: 0.1.0
Summary: A pragmatic library that transparently redirects Python's standard file operations to FSSpec backends through monkey-patching, enabling existing code to work with any filesystem without modification.
Requires-Python: >=3.10
License-File: LICENSE
Dynamic: license-file
